{
  "trace": {
    "run_id": "2026-04-04-2800",
    "timestamp": "2026-04-04T28:00Z",
    "phase": "Phase 10",
    "health": "GREEN",
    "task": "#46 - SSE reconnect with exponential backoff + session state restore on reconnect",
    "agents": {
      "coordinator": "completed",
      "architect": "completed",
      "builder": "completed",
      "qa": "pass",
      "reporter": "running"
    }
  },
  "spans": [
    {"agent": "coordinator", "status": "completed", "detail": "Selected task #46, needs_architect=true"},
    {"agent": "architect", "status": "completed", "detail": "Task spec confirmed: SSE backoff + session state restore"},
    {"agent": "builder", "status": "completed", "detail": "6 files changed: chat.py, schemas.py, routers/chat.py, chat.js, test_chat.py, test_frontend.py; +137/-22 lines"},
    {"agent": "qa", "status": "pass", "detail": "1170/1170 tests pass, ruff clean, all done criteria met"},
    {"agent": "reporter", "status": "running", "detail": "Writing logs, updating status, creating PR"}
  ],
  "ltes": {
    "latency": {"total_duration_ms": 22490},
    "traffic": {"commits": 1, "lines_added": 137, "lines_removed": 22, "files_changed": 6},
    "errors": {"test_failures": 0, "fix_attempts": 0},
    "saturation": {"backlog_remaining": 6}
  }
}
