{
  "trace": {
    "run_id": "2026-04-07-2300",
    "timestamp": "2026-04-07T23:00:00Z",
    "phase": "Phase 10: Chat + Multi-Agent Dashboard",
    "health": "GREEN",
    "task": "#107 Chat: swap_places intent — swap places between two days",
    "agents": {
      "coordinator": "completed",
      "architect": "skipped",
      "builder": "completed",
      "qa": "pass",
      "reporter": "running"
    }
  },
  "spans": [
    {
      "agent": "coordinator",
      "status": "completed",
      "detail": "Selected task #107 — swap_places intent handler. health_check: 1611/1623 (1611 passed, 12 skipped). No fix needed, no architect needed."
    },
    {
      "agent": "architect",
      "status": "skipped",
      "detail": "backlog_ready_count=2 >= 2, skip threshold met"
    },
    {
      "agent": "builder",
      "status": "completed",
      "detail": "Implemented swap_places intent. Added place_index_2 to Intent model. Handler handles in-memory and DB plans, emits day_update SSE for both days. 12 new tests added. lines_added=338, lines_removed=2."
    },
    {
      "agent": "qa",
      "status": "pass",
      "detail": "1623/1623 passed, 12 skipped. All checks: all_tests_pass, new_tests_exist, lint_clean, done_criteria_met, no_regressions, integration_test_quality, e2e_integration, no_secrets_leaked — all pass."
    },
    {
      "agent": "reporter",
      "status": "running",
      "detail": "Writing logs, updating status.md, backlog.md, error-budget.json, dashboard.json. Creating PR."
    }
  ],
  "ltes": {
    "latency": {"total_duration_ms": 50000},
    "traffic": {"commits": 1, "lines_added": 338, "lines_removed": 2, "files_changed": 2},
    "errors": {"test_failures": 0, "fix_attempts": 0},
    "saturation": {"backlog_remaining": 2}
  }
}
