{
  "trace": {
    "run_id": "2026-04-05-1200",
    "timestamp": "2026-04-05T12:00:00Z",
    "phase": "Phase 10: Chat + Multi-Agent Dashboard",
    "health": "GREEN",
    "task": "#68 - Chat: delete_expense intent handler",
    "agents": {
      "coordinator": "completed",
      "architect": "skipped",
      "builder": "completed",
      "qa": "pass",
      "reporter": "running"
    }
  },
  "spans": [
    {
      "agent": "coordinator",
      "status": "completed",
      "detail": "Selected task #68 Chat: delete_expense intent handler (github_issue: 64)"
    },
    {
      "agent": "architect",
      "status": "skipped",
      "detail": "backlog_ready_count=4 >= 2, no architect needed"
    },
    {
      "agent": "builder",
      "status": "completed",
      "detail": "Implemented _handle_delete_expense handler. Deletion priority: by name > by category > most recently added (마지막 지출). After deletion, expense_summary re-emitted. 12 new tests added. 1364/1364 tests pass, ruff clean."
    },
    {
      "agent": "qa",
      "status": "pass",
      "detail": "1364/1364 tests passed. all_tests_pass, new_tests_exist, lint_clean, done_criteria_met, no_regressions, no_secrets_leaked all PASS."
    },
    {
      "agent": "reporter",
      "status": "running",
      "detail": "Writing logs, updating status.md, backlog.md, error-budget.json, dashboard.json, creating PR"
    }
  ],
  "ltes": {
    "latency": {
      "total_duration_ms": 21640
    },
    "traffic": {
      "commits": 1,
      "lines_added": 215,
      "lines_removed": 2,
      "files_changed": 2
    },
    "errors": {
      "test_failures": 0,
      "fix_attempts": 0
    },
    "saturation": {
      "backlog_remaining": 4
    }
  }
}
